{
  "project_info": {
    "project_number": "464041488221",
    "firebase_url": "https://befriendy-e8f50.firebaseio.com",
    "project_id": "befriendy-e8f50",
    "storage_bucket": "befriendy-e8f50.appspot.com"
  },
  "client": [
    {
      "client_info": {
        "mobilesdk_app_id": "1:464041488221:android:87dc99dc265bdde3",
        "android_client_info": {
          "package_name": "com.example.xps.xps.befriendyseby"
        }
      },
      "oauth_client": [
        {
          "client_id": "464041488221-tbqqf0v676tn9jhsvcsq628lkp1a19od.apps.googleusercontent.com",
          "client_type": 3
        }
      ],
      "api_key": [
        {
          "current_key": "AIzaSyDvEZ8V5BUx_RxjnNFOZ8YH0g640XFZPt0"
        }
      ],
      "services": {
        "analytics_service": {
          "status": 1
        },
        "appinvite_service": {
          "status": 1,
          "other_platform_oauth_client": []
        },
        "ads_service": {
          "status": 2
        }
      }
    },
    {
      "client_info": {
        "mobilesdk_app_id": "1:464041488221:android:3e13d76c79b42e32",
        "android_client_info": {
          "package_name": "com.example"
        }
      },
      "oauth_client": [
        {
          "client_id": "464041488221-q8rnna4roltbpcdudl5tnl2u960tnpj9.apps.googleusercontent.com",
          "client_type": 1,
          "android_info": {
            "package_name": "com.example",
            "certificate_hash": "EB8455BBDDDC72B445DCC621B92821E8D2BEF789"
          }
        },
        {
          "client_id": "464041488221-tbqqf0v676tn9jhsvcsq628lkp1a19od.apps.googleusercontent.com",
          "client_type": 3
        }
      ],
      "api_key": [
        {
          "current_key": "AIzaSyDvEZ8V5BUx_RxjnNFOZ8YH0g640XFZPt0"
        }
      ],
      "services": {
        "analytics_service": {
          "status": 1
        },
        "appinvite_service": {
          "status": 2,
          "other_platform_oauth_client": [
            {
              "client_id": "464041488221-tbqqf0v676tn9jhsvcsq628lkp1a19od.apps.googleusercontent.com",
              "client_type": 3
            }
          ]
        },
        "ads_service": {
          "status": 2
        }
      }
    }
  ],
  "configuration_version": "1"
}